vcs_repo_mgr/__init__.py
vcs_repo_mgr/cli.py
vcs_repo_mgr/exceptions.py
vcs_repo_mgr/tests.py
vcs_repo_mgr/backends/__init__.py
vcs_repo_mgr/backends/bzr.py
vcs_repo_mgr/backends/git.py
vcs_repo_mgr/backends/hg.py
vcs_repo_mgr-4.2.dist-info/DESCRIPTION.rst
vcs_repo_mgr-4.2.dist-info/METADATA
vcs_repo_mgr-4.2.dist-info/RECORD
vcs_repo_mgr-4.2.dist-info/WHEEL
vcs_repo_mgr-4.2.dist-info/entry_points.txt
vcs_repo_mgr-4.2.dist-info/metadata.json
vcs_repo_mgr-4.2.dist-info/top_level.txt
