Metadata-Version: 2.0
Name: vcs-repo-mgr
Version: 4.2
Summary: Version control repository manager
Home-page: https://github.com/xolox/python-vcs-repo-mgr
Author: Peter Odding
Author-email: peter@peterodding.com
License: MIT
Platform: UNKNOWN
Classifier: Development Status :: 5 - Production/Stable
Classifier: Environment :: Console
Classifier: Intended Audience :: Developers
Classifier: Intended Audience :: Information Technology
Classifier: Intended Audience :: System Administrators
Classifier: License :: OSI Approved :: MIT License
Classifier: Operating System :: MacOS :: MacOS X
Classifier: Operating System :: POSIX
Classifier: Operating System :: POSIX :: Linux
Classifier: Operating System :: Unix
Classifier: Programming Language :: Python
Classifier: Programming Language :: Python :: 2
Classifier: Programming Language :: Python :: 2.6
Classifier: Programming Language :: Python :: 2.7
Classifier: Programming Language :: Python :: 3
Classifier: Programming Language :: Python :: 3.4
Classifier: Programming Language :: Python :: 3.5
Classifier: Programming Language :: Python :: 3.6
Classifier: Topic :: Software Development :: Libraries :: Python Modules
Classifier: Topic :: Software Development :: Version Control
Classifier: Topic :: System :: Archiving :: Packaging
Classifier: Topic :: System :: Software Distribution
Classifier: Topic :: System :: Systems Administration
Classifier: Topic :: Utilities
Requires-Dist: coloredlogs (>=6.1)
Requires-Dist: executor (>=1.2)
Requires-Dist: humanfriendly (>=4.8)
Requires-Dist: naturalsort (>=1.3)
Requires-Dist: property-manager (>=2.2)
Requires-Dist: six (>=1.8.0)
Requires-Dist: bzr (>=2.6.0); python_version == "2.6"
Requires-Dist: mercurial (<4.3,>=2.9); python_version == "2.6"
Requires-Dist: bzr (>=2.6.0); python_version == "2.7"
Requires-Dist: mercurial (>=2.9); python_version == "2.7"
